hierarchical_label_propagation/HLP.py
hierarchical_label_propagation/HLP_lookup_table.pt
hierarchical_label_propagation/__init__.py
hierarchical_label_propagation-0.1.0.dist-info/METADATA
hierarchical_label_propagation-0.1.0.dist-info/WHEEL
hierarchical_label_propagation-0.1.0.dist-info/licenses/LICENSE
hierarchical_label_propagation-0.1.0.dist-info/RECORD
