Metadata-Version: 2.3
Name: hierarchical-label-propagation
Version: 0.1.0
Summary: Python implementation of Hierarchical Label Propagation (HLP)
Project-URL: Homepage, https://github.com/LudovicTuncay/hierarchical-label-propagation
Project-URL: Issues, https://github.com/LudovicTuncay/hierarchical-label-propagation/issues
Author-email: Ludovic TUNCAY <ludovic.tuncay@irit.fr>
License-File: LICENSE
Keywords: HLP,Hierarchical Label Propagation,Hierarchy,Ontology
Classifier: License :: OSI Approved :: MIT License
Classifier: Operating System :: OS Independent
Classifier: Programming Language :: Python :: 3
Requires-Python: >=3.8
Requires-Dist: torch>=1.8.0
